blitz_work/__init__.py
blitz_work/atomatic.py
blitz_work/blitzcrud.py
blitz_work/fields.py
blitz_work/forms.py
blitz_work/internationalization.py
blitz_work/tests.py
blitz_work/urls.py
blitz_work/static/css/all.min.css
blitz_work/static/css/blitz.css
blitz_work/static/css/bootstrap-datetimepicker.min.css
blitz_work/static/css/bootstrap.min.css
blitz_work/static/css/bootstrap.min.css.map
blitz_work/static/css/bootstrap.min.css.map:Zone.Identifier
blitz_work/static/css/select2-bootstrap-dark.min.css
blitz_work/static/css/select2-bootstrap.min.css
blitz_work/static/css/select2.min.css
blitz_work/static/css/toggle-bootstrap-dark.min.css
blitz_work/static/css/toggle-bootstrap.min.css
blitz_work/static/doc/css/atom-one-dark-reasonable.css
blitz_work/static/doc/css/basic.css
blitz_work/static/doc/fonts/shocktherapybb_ital.ttf
blitz_work/static/doc/fonts/shocktherapybb_reg.ttf
blitz_work/static/doc/images/preview.png
blitz_work/static/doc/js/basic.js
blitz_work/static/doc/js/highlight.pack.js
blitz_work/static/js/blitz.js
blitz_work/static/js/bootstrap-datetimepicker.min.js
blitz_work/static/js/bootstrap.bundle.js
blitz_work/static/js/bootstrap.bundle.js.map
blitz_work/static/js/bootstrap.bundle.min.js
blitz_work/static/js/bootstrap.bundle.min.js.map
blitz_work/static/js/bootstrap.js
blitz_work/static/js/bootstrap.js.map
blitz_work/static/js/bootstrap.min.js
blitz_work/static/js/bootstrap.min.js.map
blitz_work/static/js/jquery-3.5.1.min.js
blitz_work/static/js/jquery-3.6.0.min.js
blitz_work/static/js/jquery-3.6.0.min.js:Zone.Identifier
blitz_work/static/js/moment.min.js
blitz_work/static/js/popper.min.js
blitz_work/static/js/popper.min.js.map
blitz_work/static/js/popper.min.js.map:Zone.Identifier
blitz_work/static/js/select2.min.js
blitz_work/static/webfonts/fa-brands-400.eot
blitz_work/static/webfonts/fa-brands-400.svg
blitz_work/static/webfonts/fa-brands-400.ttf
blitz_work/static/webfonts/fa-brands-400.woff
blitz_work/static/webfonts/fa-brands-400.woff2
blitz_work-0.6.70.dist-info/LICENSE
blitz_work-0.6.70.dist-info/METADATA
blitz_work-0.6.70.dist-info/WHEEL
blitz_work-0.6.70.dist-info/top_level.txt
blitz_work-0.6.70.dist-info/RECORD
