Metadata-Version: 2.1
Name: blitz-work
Version: 0.6.70
Summary: Django-based framework for rapid application development.
Home-page: https://github.com/VizardEdward/blitz_work
Author: Eduardo Alejandro Leyva Piñeda
Author-email: lordedward98@gmail.com
License: MIT-License
Platform: UNKNOWN
Classifier: Environment :: Web Environment
Classifier: Intended Audience :: Developers
Classifier: License :: OSI Approved :: MIT License
Classifier: Operating System :: OS Independent
Classifier: Programming Language :: Python
Classifier: Programming Language :: Python :: 3
Classifier: Programming Language :: Python :: 3 :: Only
Classifier: Programming Language :: Python :: 3.6
Classifier: Programming Language :: Python :: 3.7
Classifier: Programming Language :: Python :: 3.8
Classifier: Programming Language :: Python :: 3.9
Requires-Python: >=3.9
License-File: LICENSE
